<?xml version="1.0" encoding="utf-8"?>
<List xmlns:ows="Microsoft SharePoint" Title="Todos" FolderCreation="FALSE" Direction="$Resources:Direction;" Url="Lists/Todos" BaseType="0" xmlns="http://schemas.microsoft.com/sharepoint/" EnableContentTypes="TRUE">
  <MetaData>
    <ContentTypes>
      
      
    <ContentType ID="0x01000F74FF152F0E4524A4EBB3D23BAC8203" Name="Todo" Group="TODOs content types" Description="Content type for TODOs items" Inherits="TRUE" Version="0"><FieldRefs><FieldRef ID="{35363960-D998-4aad-B7E8-058DFE2C669E}" DisplayName="Completed" Hidden="TRUE" Name="Completed" Sealed="TRUE" /></FieldRefs></ContentType></ContentTypes>
    <Fields>
      
    <Field ID="{fa564e0f-0c70-4ab9-b863-0177e6ddd247}" Type="Text" Name="Title" DisplayName="$Resources:core,Title;" Required="TRUE" SourceID="http://schemas.microsoft.com/sharepoint/v3" StaticName="Title" MaxLength="255" /><Field ID="{35363960-D998-4aad-B7E8-058DFE2C669E}" Name="Completed" SourceID="http://schemas.microsoft.com/sharepoint/v3" StaticName="Completed" Group="$Resources:core,Base_Columns;" Type="Boolean" DisplayName="Completed" Hidden="TRUE" Sealed="TRUE"><Default>FALSE</Default></Field></Fields>
    <Views>
      
      
    <View BaseViewID="0" Type="HTML" MobileView="TRUE" TabularView="FALSE">
        <Toolbar Type="Standard" />
        <XslLink Default="TRUE">main.xsl</XslLink>
        <RowLimit Paged="TRUE">30</RowLimit>
        <ViewFields>
          
        <FieldRef Name="LinkTitleNoMenu"></FieldRef></ViewFields>
        <Query>
          <OrderBy>
            
          <FieldRef Name="Modified" Ascending="FALSE"></FieldRef></OrderBy>
        </Query>
        <ParameterBindings>
          <ParameterBinding Name="AddNewAnnouncement" Location="Resource(wss,addnewitem)" />
          <ParameterBinding Name="NoAnnouncements" Location="Resource(wss,noXinviewofY_LIST)" />
          <ParameterBinding Name="NoAnnouncementsHowTo" Location="Resource(wss,noXinviewofY_ONET_HOME)" />
        </ParameterBindings>
      </View><View BaseViewID="1" Type="HTML" WebPartZoneID="Main" DisplayName="$Resources:core,objectiv_schema_mwsidcamlidC24;" DefaultView="TRUE" MobileView="TRUE" MobileDefaultView="TRUE" SetupPath="pages\viewpage.aspx" ImageUrl="/_layouts/15/images/generic.png?rev=23" Url="AllItems.aspx">
        <Toolbar Type="Standard" />
        <XslLink Default="TRUE">main.xsl</XslLink>
        <JSLink>clienttemplates.js</JSLink>
        <RowLimit Paged="TRUE">30</RowLimit>
        <ViewFields>
          
        <FieldRef Name="LinkTitle"></FieldRef></ViewFields>
        <Query>
          <OrderBy>
            
          <FieldRef Name="ID"></FieldRef></OrderBy>
        </Query>
        <ParameterBindings>
          <ParameterBinding Name="NoAnnouncements" Location="Resource(wss,noXinviewofY_LIST)" />
          <ParameterBinding Name="NoAnnouncementsHowTo" Location="Resource(wss,noXinviewofY_DEFAULT)" />
        </ParameterBindings>
      </View></Views>
    <Forms>
      <Form Type="DisplayForm" Url="DispForm.aspx" SetupPath="pages\form.aspx" WebPartZoneID="Main" />
      <Form Type="EditForm" Url="EditForm.aspx" SetupPath="pages\form.aspx" WebPartZoneID="Main" />
      <Form Type="NewForm" Url="NewForm.aspx" SetupPath="pages\form.aspx" WebPartZoneID="Main" />
    </Forms>
  </MetaData>
</List>